quark/__init__.py
quark/__main__.py
quark/argument_parsing.py
quark/benchmarking.py
quark/config_parsing.py
quark/core.py
quark/quark_logging.py
quark/interface_types/__init__.py
quark/interface_types/circuit.py
quark/interface_types/graph.py
quark/interface_types/ising.py
quark/interface_types/lp.py
quark/interface_types/other.py
quark/interface_types/quantum_result.py
quark/interface_types/qubo.py
quark/plugin_manager/factory.py
quark/plugin_manager/loader.py
quark_framework-0.4.6.dist-info/licenses/LICENSE
quark_framework-0.4.6.dist-info/licenses/NOTICE
quark_framework-0.4.6.dist-info/METADATA
quark_framework-0.4.6.dist-info/WHEEL
quark_framework-0.4.6.dist-info/entry_points.txt
quark_framework-0.4.6.dist-info/top_level.txt
quark_framework-0.4.6.dist-info/RECORD
