Metadata-Version: 2.4
Name: QUARK-framework
Version: 0.4.6
Summary: Framework for Quantum Computing Application Benchmarking
Author-email: Philipp Ross <philipp.ross@bmw.de>, Marvin Erdmann <marvin.erdmann@bmw.de>, Andre Luckow <andre.luckow@bmwgroup.com>, Greshma Shaji <greshma.shaji@bmwgroup.com>, Florian Kiwit <florian.kiwit@bmw.de>, Benjamin Decker <benjamin.decker@bmw.de>
License-Expression: Apache-2.0
Project-URL: Homepage, https://github.com/QUARK-framework/QUARK-framework
Project-URL: Issues, https://github.com/QUARK-framework/QUARK-framework/issues
Classifier: Programming Language :: Python :: 3
Classifier: Operating System :: OS Independent
Requires-Python: >=3.12
License-File: LICENSE
License-File: NOTICE
Requires-Dist: anytree>=2.13.0
Requires-Dist: inquirer>=3.4.0
Requires-Dist: matplotlib>=3.10.1
Requires-Dist: networkx>=3.4.2
Requires-Dist: notebook>=7.4.4
Requires-Dist: packaging>=24.2
Requires-Dist: pyyaml>=6.0.2
Dynamic: license-file
